lgpio.py
lgpio-0.0.0.2.dist-info/LICENSE
lgpio-0.0.0.2.dist-info/METADATA
lgpio-0.0.0.2.dist-info/WHEEL
lgpio-0.0.0.2.dist-info/top_level.txt
lgpio-0.0.0.2.dist-info/RECORD
